{"recordInfo": {"propertyRight": "Industrial design", "reportType": "Total count by filing office", "yearRange": "2010 - 2024", "indicator": "1 - Total design applications (direct and via the Hague system)"}, "columns": [{"code": "selectedOffice", "sortProperty": "selectedOffice_SeqOrder", "value": "Office", "type": "text"}, {"code": "2010", "sortProperty": "2010_SeqOrder", "value": "2010", "type": "number"}, {"code": "2011", "sortProperty": "2011_SeqOrder", "value": "2011", "type": "number"}, {"code": "2012", "sortProperty": "2012_SeqOrder", "value": "2012", "type": "number"}, {"code": "2013", "sortProperty": "2013_SeqOrder", "value": "2013", "type": "number"}, {"code": "2014", "sortProperty": "2014_SeqOrder", "value": "2014", "type": "number"}, {"code": "2015", "sortProperty": "2015_SeqOrder", "value": "2015", "type": "number"}, {"code": "2016", "sortProperty": "2016_SeqOrder", "value": "2016", "type": "number"}, {"code": "2017", "sortProperty": "2017_SeqOrder", "value": "2017", "type": "number"}, {"code": "2018", "sortProperty": "2018_SeqOrder", "value": "2018", "type": "number"}, {"code": "2019", "sortProperty": "2019_SeqOrder", "value": "2019", "type": "number"}, {"code": "2020", "sortProperty": "2020_SeqOrder", "value": "2020", "type": "number"}, {"code": "2021", "sortProperty": "2021_SeqOrder", "value": "2021", "type": "number"}, {"code": "2022", "sortProperty": "2022_SeqOrder", "value": "2022", "type": "number"}, {"code": "2023", "sortProperty": "2023_SeqOrder", "value": "2023", "type": "number"}, {"code": "2024", "sortProperty": "2024_SeqOrder", "value": "2024", "type": "number"}], "records": [{"selectedOffice_SeqOrder": 123, "2020_SeqOrder": 440.0, "2012": "297,303,6", "2011": "2,307,309", "2011_SeqOrder": 618.0, "2010": "279,286,7", "2012_SeqOrder": 606.0, "2024": "252,257,5", "2014_SeqOrder": 414.0, "2017_SeqOrder": 372.0, "2023_SeqOrder": 572.0, "2010_SeqOrder": 572.0, "2013_SeqOrder": 338.0, "2016_SeqOrder": 340.0, "2023": "242,286,44", "2022": "22,338,360", "2021": "328,328", "2020": "13,207,220", "2019_SeqOrder": 636.0, "2021_SeqOrder": 656.0, "2019": "314,318,4", "2018": "293,300,7", "2018_SeqOrder": 600.0, "2015_SeqOrder": 412.0, "2017": "163,186,23", "2016": "166,170,4", "2024_SeqOrder": 514.0, "2015": "1,205,206", "2014": "203,207,4", "2013": "165,169,4", "2022_SeqOrder": 720.0, "selectedOffice": "Madagascar"}]}