{"recordInfo": {"propertyRight": "Trademark", "reportType": "Total count by filing office", "yearRange": "2010 - 2024", "indicator": "1 - Total trademark applications (direct and via the Madrid system)"}, "columns": [{"code": "selectedOffice", "sortProperty": "selectedOffice_SeqOrder", "value": "Office", "type": "text"}, {"code": "2010", "sortProperty": "2010_SeqOrder", "value": "2010", "type": "number"}, {"code": "2011", "sortProperty": "2011_SeqOrder", "value": "2011", "type": "number"}, {"code": "2012", "sortProperty": "2012_SeqOrder", "value": "2012", "type": "number"}, {"code": "2013", "sortProperty": "2013_SeqOrder", "value": "2013", "type": "number"}, {"code": "2014", "sortProperty": "2014_SeqOrder", "value": "2014", "type": "number"}, {"code": "2015", "sortProperty": "2015_SeqOrder", "value": "2015", "type": "number"}, {"code": "2016", "sortProperty": "2016_SeqOrder", "value": "2016", "type": "number"}, {"code": "2017", "sortProperty": "2017_SeqOrder", "value": "2017", "type": "number"}, {"code": "2018", "sortProperty": "2018_SeqOrder", "value": "2018", "type": "number"}, {"code": "2019", "sortProperty": "2019_SeqOrder", "value": "2019", "type": "number"}, {"code": "2020", "sortProperty": "2020_SeqOrder", "value": "2020", "type": "number"}, {"code": "2021", "sortProperty": "2021_SeqOrder", "value": "2021", "type": "number"}, {"code": "2022", "sortProperty": "2022_SeqOrder", "value": "2022", "type": "number"}, {"code": "2023", "sortProperty": "2023_SeqOrder", "value": "2023", "type": "number"}, {"code": "2024", "sortProperty": "2024_SeqOrder", "value": "2024", "type": "number"}], "records": [{"selectedOffice_SeqOrder": 148, "2020_SeqOrder": 9324.0, "2012": "17182,17182", "2011": "20560,20560", "2011_SeqOrder": 41120.0, "2010": null, "2012_SeqOrder": 34364.0, "2024": null, "2014_SeqOrder": null, "2017_SeqOrder": 47758.0, "2023_SeqOrder": null, "2010_SeqOrder": null, "2013_SeqOrder": 38664.0, "2016_SeqOrder": 33823.0, "2023": null, "2022": null, "2021": null, "2020": "9324", "2019_SeqOrder": 37316.0, "2021_SeqOrder": null, "2019": "11341,18658,7317", "2018": "11221,20725,9504", "2018_SeqOrder": 41450.0, "2015_SeqOrder": null, "2017": "15557,23879,8322", "2016": "33823", "2024_SeqOrder": null, "2015": null, "2014": null, "2013": "19332,19332", "2022_SeqOrder": null, "selectedOffice": "Nigeria"}]}