{"recordInfo": {"propertyRight": "Trademark", "reportType": "Total count by filing office", "yearRange": "2010 - 2024", "indicator": "2 - Total trademark registrations (direct and via the Madrid system)"}, "columns": [{"code": "selectedOffice", "sortProperty": "selectedOffice_SeqOrder", "value": "Office", "type": "text"}, {"code": "2010", "sortProperty": "2010_SeqOrder", "value": "2010", "type": "number"}, {"code": "2011", "sortProperty": "2011_SeqOrder", "value": "2011", "type": "number"}, {"code": "2012", "sortProperty": "2012_SeqOrder", "value": "2012", "type": "number"}, {"code": "2013", "sortProperty": "2013_SeqOrder", "value": "2013", "type": "number"}, {"code": "2014", "sortProperty": "2014_SeqOrder", "value": "2014", "type": "number"}, {"code": "2015", "sortProperty": "2015_SeqOrder", "value": "2015", "type": "number"}, {"code": "2016", "sortProperty": "2016_SeqOrder", "value": "2016", "type": "number"}, {"code": "2017", "sortProperty": "2017_SeqOrder", "value": "2017", "type": "number"}, {"code": "2018", "sortProperty": "2018_SeqOrder", "value": "2018", "type": "number"}, {"code": "2019", "sortProperty": "2019_SeqOrder", "value": "2019", "type": "number"}, {"code": "2020", "sortProperty": "2020_SeqOrder", "value": "2020", "type": "number"}, {"code": "2021", "sortProperty": "2021_SeqOrder", "value": "2021", "type": "number"}, {"code": "2022", "sortProperty": "2022_SeqOrder", "value": "2022", "type": "number"}, {"code": "2023", "sortProperty": "2023_SeqOrder", "value": "2023", "type": "number"}, {"code": "2024", "sortProperty": "2024_SeqOrder", "value": "2024", "type": "number"}], "records": [{"selectedOffice_SeqOrder": 160, "2020_SeqOrder": 46410.0, "2012": "11308,18531,7223", "2011": "18607", "2011_SeqOrder": 18607.0, "2010": "11167,17937,6770", "2012_SeqOrder": 37062.0, "2024": "23581,31028,7447", "2014_SeqOrder": 43880.0, "2017_SeqOrder": 53570.0, "2023_SeqOrder": 55780.0, "2010_SeqOrder": 35874.0, "2013_SeqOrder": 39028.0, "2016_SeqOrder": 42814.0, "2023": "20917,27890,6973", "2022": "21588,29489,7901", "2021": "22441,30277,7836", "2020": "16806,23205,6399", "2019_SeqOrder": 60222.0, "2021_SeqOrder": 60554.0, "2019": "22486,30111,7625", "2018": "18552,26283,7731", "2018_SeqOrder": 52566.0, "2015_SeqOrder": 42004.0, "2017": "18021,26785,8764", "2016": "13915,21407,7492", "2024_SeqOrder": 62056.0, "2015": "13400,21002,7602", "2014": "13175,21940,8765", "2013": "11559,19514,7955", "2022_SeqOrder": 58978.0, "selectedOffice": "Peru"}]}