{"recordInfo": {"propertyRight": "Industrial design", "reportType": "Total count by filing office", "yearRange": "2010 - 2024", "indicator": "2 - Total design registrations (direct and via the Hague system)"}, "columns": [{"code": "selectedOffice", "sortProperty": "selectedOffice_SeqOrder", "value": "Office", "type": "text"}, {"code": "2010", "sortProperty": "2010_SeqOrder", "value": "2010", "type": "number"}, {"code": "2011", "sortProperty": "2011_SeqOrder", "value": "2011", "type": "number"}, {"code": "2012", "sortProperty": "2012_SeqOrder", "value": "2012", "type": "number"}, {"code": "2013", "sortProperty": "2013_SeqOrder", "value": "2013", "type": "number"}, {"code": "2014", "sortProperty": "2014_SeqOrder", "value": "2014", "type": "number"}, {"code": "2015", "sortProperty": "2015_SeqOrder", "value": "2015", "type": "number"}, {"code": "2016", "sortProperty": "2016_SeqOrder", "value": "2016", "type": "number"}, {"code": "2017", "sortProperty": "2017_SeqOrder", "value": "2017", "type": "number"}, {"code": "2018", "sortProperty": "2018_SeqOrder", "value": "2018", "type": "number"}, {"code": "2019", "sortProperty": "2019_SeqOrder", "value": "2019", "type": "number"}, {"code": "2020", "sortProperty": "2020_SeqOrder", "value": "2020", "type": "number"}, {"code": "2021", "sortProperty": "2021_SeqOrder", "value": "2021", "type": "number"}, {"code": "2022", "sortProperty": "2022_SeqOrder", "value": "2022", "type": "number"}, {"code": "2023", "sortProperty": "2023_SeqOrder", "value": "2023", "type": "number"}, {"code": "2024", "sortProperty": "2024_SeqOrder", "value": "2024", "type": "number"}], "records": [{"selectedOffice_SeqOrder": 163, "2020_SeqOrder": 704.0, "2012": "33,385,418", "2011": "10,401,411", "2011_SeqOrder": 822.0, "2010": "17,384,401", "2012_SeqOrder": 836.0, "2024": "17,216,233", "2014_SeqOrder": 780.0, "2017_SeqOrder": 676.0, "2023_SeqOrder": 330.0, "2010_SeqOrder": 802.0, "2013_SeqOrder": 772.0, "2016_SeqOrder": 836.0, "2023": "148,165,17", "2022": "14,193,207", "2021": "14,228,242", "2020": "103,249,352", "2019_SeqOrder": 604.0, "2021_SeqOrder": 484.0, "2019": "272,30,302", "2018": "245,254,9", "2018_SeqOrder": 508.0, "2015_SeqOrder": 786.0, "2017": "305,33,338", "2016": "337,418,81", "2024_SeqOrder": 466.0, "2015": "20,373,393", "2014": "17,373,390", "2013": "13,373,386", "2022_SeqOrder": 414.0, "selectedOffice": "Portugal"}]}