{"recordInfo": {"propertyRight": "Patent", "reportType": "Total count by filing office", "yearRange": "2010 - 2024", "indicator": "1 - Total patent applications (direct and PCT national phase entries)"}, "columns": [{"code": "selectedOffice", "sortProperty": "selectedOffice_SeqOrder", "value": "Office", "type": "text"}, {"code": "2010", "sortProperty": "2010_SeqOrder", "value": "2010", "type": "number"}, {"code": "2011", "sortProperty": "2011_SeqOrder", "value": "2011", "type": "number"}, {"code": "2012", "sortProperty": "2012_SeqOrder", "value": "2012", "type": "number"}, {"code": "2013", "sortProperty": "2013_SeqOrder", "value": "2013", "type": "number"}, {"code": "2014", "sortProperty": "2014_SeqOrder", "value": "2014", "type": "number"}, {"code": "2015", "sortProperty": "2015_SeqOrder", "value": "2015", "type": "number"}, {"code": "2016", "sortProperty": "2016_SeqOrder", "value": "2016", "type": "number"}, {"code": "2017", "sortProperty": "2017_SeqOrder", "value": "2017", "type": "number"}, {"code": "2018", "sortProperty": "2018_SeqOrder", "value": "2018", "type": "number"}, {"code": "2019", "sortProperty": "2019_SeqOrder", "value": "2019", "type": "number"}, {"code": "2020", "sortProperty": "2020_SeqOrder", "value": "2020", "type": "number"}, {"code": "2021", "sortProperty": "2021_SeqOrder", "value": "2021", "type": "number"}, {"code": "2022", "sortProperty": "2022_SeqOrder", "value": "2022", "type": "number"}, {"code": "2023", "sortProperty": "2023_SeqOrder", "value": "2023", "type": "number"}, {"code": "2024", "sortProperty": "2024_SeqOrder", "value": "2024", "type": "number"}], "records": [{"selectedOffice_SeqOrder": 183, "2020_SeqOrder": 442.0, "2012": "168,203,35", "2011": "224,257,33", "2011_SeqOrder": 514.0, "2010": "234,282,48", "2012_SeqOrder": 406.0, "2024": "10,167,177", "2014_SeqOrder": 468.0, "2017_SeqOrder": 412.0, "2023_SeqOrder": 512.0, "2010_SeqOrder": 564.0, "2013_SeqOrder": 420.0, "2016_SeqOrder": 470.0, "2023": "232,24,256", "2022": "184,19,203", "2021": "13,146,159", "2020": "15,206,221", "2019_SeqOrder": 468.0, "2021_SeqOrder": 318.0, "2019": "206,234,28", "2018": "14,217,231", "2018_SeqOrder": 462.0, "2015_SeqOrder": 512.0, "2017": "183,206,23", "2016": "15,220,235", "2024_SeqOrder": 354.0, "2015": "228,256,28", "2014": "211,23,234", "2013": "184,210,26", "2022_SeqOrder": 406.0, "selectedOffice": "Slovakia"}]}