{"recordInfo": {"propertyRight": "Patent", "reportType": "Total count by filing office", "yearRange": "2010 - 2024", "indicator": "2 - Total patent grants (direct and PCT national phase entries)"}, "columns": [{"code": "selectedOffice", "sortProperty": "selectedOffice_SeqOrder", "value": "Office", "type": "text"}, {"code": "2010", "sortProperty": "2010_SeqOrder", "value": "2010", "type": "number"}, {"code": "2011", "sortProperty": "2011_SeqOrder", "value": "2011", "type": "number"}, {"code": "2012", "sortProperty": "2012_SeqOrder", "value": "2012", "type": "number"}, {"code": "2013", "sortProperty": "2013_SeqOrder", "value": "2013", "type": "number"}, {"code": "2014", "sortProperty": "2014_SeqOrder", "value": "2014", "type": "number"}, {"code": "2015", "sortProperty": "2015_SeqOrder", "value": "2015", "type": "number"}, {"code": "2016", "sortProperty": "2016_SeqOrder", "value": "2016", "type": "number"}, {"code": "2017", "sortProperty": "2017_SeqOrder", "value": "2017", "type": "number"}, {"code": "2018", "sortProperty": "2018_SeqOrder", "value": "2018", "type": "number"}, {"code": "2019", "sortProperty": "2019_SeqOrder", "value": "2019", "type": "number"}, {"code": "2020", "sortProperty": "2020_SeqOrder", "value": "2020", "type": "number"}, {"code": "2021", "sortProperty": "2021_SeqOrder", "value": "2021", "type": "number"}, {"code": "2022", "sortProperty": "2022_SeqOrder", "value": "2022", "type": "number"}, {"code": "2023", "sortProperty": "2023_SeqOrder", "value": "2023", "type": "number"}, {"code": "2024", "sortProperty": "2024_SeqOrder", "value": "2024", "type": "number"}], "records": [{"selectedOffice_SeqOrder": 217, "2020_SeqOrder": 8638.0, "2012": "1016,1068,52", "2011": "1006,48,958", "2011_SeqOrder": 2012.0, "2010": "29,793,822", "2012_SeqOrder": 2136.0, "2024": "308,4122,4430", "2014_SeqOrder": 2794.0, "2017_SeqOrder": 3490.0, "2023_SeqOrder": 7336.0, "2010_SeqOrder": 1644.0, "2013_SeqOrder": 2364.0, "2016_SeqOrder": 2846.0, "2023": "315,3353,3668", "2022": "153,3715,3868", "2021": "153,3538,3691", "2020": "139,4180,4319", "2019_SeqOrder": 5240.0, "2021_SeqOrder": 7382.0, "2019": "169,2451,2620", "2018": "2014,205,2219", "2018_SeqOrder": 4438.0, "2015_SeqOrder": 2776.0, "2017": "111,1634,1745", "2016": "1347,1423,76", "2024_SeqOrder": 8860.0, "2015": "1325,1388,63", "2014": "1361,1397,36", "2013": "1123,1182,59", "2022_SeqOrder": 7736.0, "selectedOffice": "Viet Nam"}]}