{"recordInfo": {"propertyRight": "Industrial design", "reportType": "Total count by filing office", "yearRange": "2010 - 2024", "indicator": "1 - Total design applications (direct and via the Hague system)"}, "columns": [{"code": "selectedOffice", "sortProperty": "selectedOffice_SeqOrder", "value": "Office", "type": "text"}, {"code": "2010", "sortProperty": "2010_SeqOrder", "value": "2010", "type": "number"}, {"code": "2011", "sortProperty": "2011_SeqOrder", "value": "2011", "type": "number"}, {"code": "2012", "sortProperty": "2012_SeqOrder", "value": "2012", "type": "number"}, {"code": "2013", "sortProperty": "2013_SeqOrder", "value": "2013", "type": "number"}, {"code": "2014", "sortProperty": "2014_SeqOrder", "value": "2014", "type": "number"}, {"code": "2015", "sortProperty": "2015_SeqOrder", "value": "2015", "type": "number"}, {"code": "2016", "sortProperty": "2016_SeqOrder", "value": "2016", "type": "number"}, {"code": "2017", "sortProperty": "2017_SeqOrder", "value": "2017", "type": "number"}, {"code": "2018", "sortProperty": "2018_SeqOrder", "value": "2018", "type": "number"}, {"code": "2019", "sortProperty": "2019_SeqOrder", "value": "2019", "type": "number"}, {"code": "2020", "sortProperty": "2020_SeqOrder", "value": "2020", "type": "number"}, {"code": "2021", "sortProperty": "2021_SeqOrder", "value": "2021", "type": "number"}, {"code": "2022", "sortProperty": "2022_SeqOrder", "value": "2022", "type": "number"}, {"code": "2023", "sortProperty": "2023_SeqOrder", "value": "2023", "type": "number"}, {"code": "2024", "sortProperty": "2024_SeqOrder", "value": "2024", "type": "number"}], "records": [{"selectedOffice_SeqOrder": 222, "2020_SeqOrder": 248.0, "2012": "12,3,9", "2011": "13,16,3", "2011_SeqOrder": 32.0, "2010": "1,7,8", "2012_SeqOrder": 24.0, "2024": "71,71", "2014_SeqOrder": 80.0, "2017_SeqOrder": 60.0, "2023_SeqOrder": 336.0, "2010_SeqOrder": 16.0, "2013_SeqOrder": 86.0, "2016_SeqOrder": 138.0, "2023": "1,167,168", "2022": "42,42", "2021": "46,46", "2020": "124,124", "2019_SeqOrder": 116.0, "2021_SeqOrder": 92.0, "2019": "58,58", "2018": "39,39", "2018_SeqOrder": 78.0, "2015_SeqOrder": 42.0, "2017": "30,30", "2016": "1,68,69", "2024_SeqOrder": 142.0, "2015": "21,21", "2014": "11,29,40", "2013": "3,40,43", "2022_SeqOrder": 84.0, "selectedOffice": "Zambia"}]}